README.md
setup.py
scripts/tg-graph-show
scripts/tg-graph-to-turtle
scripts/tg-init-pulsar
scripts/tg-init-pulsar-manager
scripts/tg-load-pdf
scripts/tg-load-text
scripts/tg-processor-state
scripts/tg-query-document-rag
scripts/tg-query-graph-rag
trustgraph/utils_version.py
trustgraph_utils.egg-info/PKG-INFO
trustgraph_utils.egg-info/SOURCES.txt
trustgraph_utils.egg-info/dependency_links.txt
trustgraph_utils.egg-info/requires.txt
trustgraph_utils.egg-info/top_level.txt