Metadata-Version: 2.1
Name: trustgraph-utils
Version: 0.11.12
Summary: TrustGraph provides a means to run a pipeline of flexible AI processing components in a flexible means to achieve a processing pipeline.
Home-page: https://github.com/trustgraph-ai/trustgraph
Download-URL: https://github.com/trustgraph-ai/trustgraph/archive/refs/tags/v0.11.12.tar.gz
Author: trustgraph.ai
Author-email: security@trustgraph.ai
Classifier: Programming Language :: Python :: 3
Classifier: License :: OSI Approved :: GNU General Public License v3 or later (GPLv3+)
Classifier: Operating System :: OS Independent
Requires-Python: >=3.8
Requires-Dist: trustgraph-base
Requires-Dist: requests
Requires-Dist: pulsar-client
Requires-Dist: tabulate
